{
  "appPageId" : "33545492-13c4-4c9b-83c3-4966dcb97e8d",
  "componentName" : "siteforce:dynamicLayout",
  "dataProviders" : [ ],
  "id" : "d7fb116a-76e1-4a00-9e5b-ea13a9e5351f",
  "label" : "Enablement Program Detail",
  "regions" : [ {
    "id" : "3d2ef8f0-0afa-4ed2-81c2-52acdbbb1b6e",
    "regionName" : "header",
    "type" : "region"
  }, {
    "components" : [ {
      "componentAttributes" : {
        "background" : "background: rgba(0,0,0,0)",
        "backgroundOverlay" : "rgba(0,0,0,0.5)",
        "contentAreaWidth" : 100,
        "sectionConfig" : {
          "UUID" : "dcf031ff-c851-4648-8731-59cdccec2dae",
          "columns" : [ {
            "UUID" : "0ce1514c-bd09-4ad0-91c3-b38c99a5d4a1",
            "columnKey" : "col1",
            "columnName" : "column 1",
            "columnWidth" : "12",
            "seedComponents" : [ {
              "attributes" : {
                "sfdc:identifier" : "runtime_ses_ext_programDetailHeader"
              },
              "fqn" : "runtime_ses_ext:programDetailHeader"
            }, {
              "attributes" : {
                "displayAsCard" : "true",
                "sfdc:identifier" : "runtime_ses_ext_programOutcomeCard"
              },
              "fqn" : "runtime_ses_ext:programOutcomeCard"
            }, {
              "attributes" : {
                "displayAsCard" : "true",
                "sfdc:identifier" : "runtime_ses_ext_programTaskListCard"
              },
              "fqn" : "runtime_ses_ext:programTaskListCard"
            } ]
          } ]
        },
        "sectionHeight" : 32
      },
      "componentName" : "forceCommunity:section",
      "id" : "dcf031ff-c851-4648-8731-59cdccec2dae",
      "regions" : [ {
        "components" : [ {
          "componentAttributes" : {
            "displayAsCard" : false,
            "displayMode" : "expanded",
            "recordId" : "{!recordId}",
            "showDescription" : true,
            "showDueDate" : true,
            "titleHeadingLevel" : "h1"
          },
          "componentName" : "runtime_ses_ext:programDetailHeader",
          "id" : "fc6131e9-b712-4ed2-99d4-704cc735c8c1",
          "renderPriority" : "NEUTRAL",
          "renditionMap" : { },
          "type" : "component"
        }, {
          "componentAttributes" : {
            "displayAsCard" : true,
            "recordId" : "{!recordId}",
            "showDescription" : true,
            "showDueDate" : true,
            "showIcon" : true,
            "title" : "Program Outcome",
            "titleHeadingLevel" : "h2",
            "titleStyle" : "small"
          },
          "componentName" : "runtime_ses_ext:programOutcomeCard",
          "id" : "4503874b-232a-4276-b895-de5be5185bf1",
          "renderPriority" : "NEUTRAL",
          "renditionMap" : { },
          "type" : "component"
        }, {
          "componentAttributes" : {
            "displayAsCard" : true,
            "recordId" : "{!recordId}",
            "showDescription" : true,
            "showDueDate" : true,
            "showExpandOrCollapseButtons" : true,
            "showIcons" : true,
            "showProgress" : true,
            "title" : "Milestones and Tasks",
            "titleHeadingLevel" : "h2",
            "titleStyle" : "small"
          },
          "componentName" : "runtime_ses_ext:programTaskListCard",
          "id" : "ec3e4693-bcb2-4099-ba21-35ff0ce95c13",
          "renderPriority" : "NEUTRAL",
          "renditionMap" : { },
          "type" : "component"
        } ],
        "id" : "0ce1514c-bd09-4ad0-91c3-b38c99a5d4a1",
        "regionLabel" : "column 1",
        "regionName" : "col1",
        "renditionMap" : { },
        "type" : "region"
      } ],
      "renderPriority" : "NEUTRAL",
      "renditionMap" : { },
      "type" : "component"
    } ],
    "id" : "4bc025dd-f582-440b-b5c6-f59946e11496",
    "regionName" : "content",
    "type" : "region"
  }, {
    "id" : "64598a38-8869-4b14-8be4-33ed6b0dfb6a",
    "regionName" : "footer",
    "type" : "region"
  }, {
    "components" : [ {
      "componentAttributes" : {
        "customHeadTags" : "",
        "description" : "",
        "title" : "{!Record._Object}: {!Record._Title}"
      },
      "componentName" : "forceCommunity:seoAssistant",
      "id" : "bd394b4b-97cd-41c8-9960-f4df948baab2",
      "renditionMap" : { },
      "type" : "component"
    } ],
    "id" : "5dfcc9de-fc34-497d-8dc9-cc0613f496ac",
    "regionName" : "sfdcHiddenRegion",
    "type" : "region"
  } ],
  "themeLayoutType" : "Inner",
  "type" : "view",
  "viewType" : "detail-0Qo"
}