{
  "assembled_at": "2026-04-09T05:37:17.000850Z",
  "feature_flags": {
    "qb": true,
    "billing": true,
    "billing_ui": true,
    "tax": true,
    "rating": true,
    "rates": true,
    "clm": true,
    "dro": true,
    "guidedselling": false,
    "ramps": true,
    "tso": false,
    "prm": true,
    "agents": false,
    "docgen": true,
    "payments": true,
    "constraints": true,
    "analytics": true,
    "procedureplans": true,
    "large_stx": true,
    "collections": false
  },
  "assembled": [
    {
      "type": "flexipage",
      "name": "RLM_Account_Record_Page.flexipage-meta.xml",
      "dest": "unpackaged/post_ux/flexipages/RLM_Account_Record_Page.flexipage-meta.xml",
      "source": "templates/flexipages/standalone/quantumbit/RLM_Account_Record_Page.flexipage-meta.xml",
      "patches": [
        {
          "feature": "utils",
          "patch_type": "insert_action",
          "description": "insert actions: Account.RLM_QuickQuote"
        },
        {
          "feature": "large_stx",
          "patch_type": "insert_action",
          "description": "insert actions: Account.RLM_Set_Up_Quote"
        }
      ]
    }
  ],
  "skipped": []
}